LICENSE
LICENSE-SAMPLECODE
LICENSE-SUMMARY
README.md
setup.cfg
setup.py
d2dl.egg-info/PKG-INFO
d2dl.egg-info/SOURCES.txt
d2dl.egg-info/dependency_links.txt
d2dl.egg-info/requires.txt
d2dl.egg-info/top_level.txt
d2dl.egg-info/zip-safe
d2l/__init__.py
d2l/jax.py
d2l/mxnet.py
d2l/tensorflow.py
d2l/torch.py