Metadata-Version: 2.4
Name: d2dl
Version: 1.1
Summary: Dive into Deep Learning
Home-page: https://d2l.ai
Author: D2L Developers
Author-email: d2l.devs@gmail.com
License: MIT-0
Requires-Python: >=3.8
License-File: LICENSE
License-File: LICENSE-SAMPLECODE
License-File: LICENSE-SUMMARY
Requires-Dist: jupyter>=1.0.0
Requires-Dist: numpy>=1.26.3
Requires-Dist: matplotlib>=3.8.2
Requires-Dist: matplotlib-inline>=0.1.6
Requires-Dist: requests>=2.31.0
Requires-Dist: pandas>=2.2.0
Requires-Dist: scipy>=1.12.0
Dynamic: author
Dynamic: author-email
Dynamic: home-page
Dynamic: license
Dynamic: license-file
Dynamic: requires-dist
Dynamic: requires-python
Dynamic: summary
